nomespah/__init__.py
nomespah/adjectives.py
nomespah/alphabets.py
nomespah/namegenerator.py
nomespah/names.py
nomespah-0.0.2.dist-info/LICENSE
nomespah-0.0.2.dist-info/METADATA
nomespah-0.0.2.dist-info/WHEEL
nomespah-0.0.2.dist-info/top_level.txt
nomespah-0.0.2.dist-info/RECORD
