Metadata-Version: 2.1
Name: nomespah
Version: 0.0.2
Summary: A name generator for tests and experiments
Home-page: https://github.com/pypa/sampleproject
Author: Pedro
Author-email: pjgs.sousa@gmail.com
License: UNKNOWN
Platform: UNKNOWN
Classifier: Programming Language :: Python :: 3
Classifier: License :: OSI Approved :: MIT License
Classifier: Operating System :: OS Independent
Requires-Python: >=3.6
License-File: LICENSE
